pdm_pfsc-0.13.3.dist-info/METADATA
pdm_pfsc-0.13.3.dist-info/WHEEL
pdm_pfsc-0.13.3.dist-info/entry_points.txt
pdm_pfsc-0.13.3.dist-info/licenses/LICENSE
pdm_pfsc/__init__.py
pdm_pfsc/abstractions.py
pdm_pfsc/actions.py
pdm_pfsc/config.py
pdm_pfsc/hook.py
pdm_pfsc/logging.py
pdm_pfsc/proc.py
pdm_pfsc/py.typed
pdm_pfsc-0.13.3.dist-info/RECORD
