Metadata-Version: 2.1
Name: pdm-pfsc
Version: 0.13.3
Summary: Core functionPlug-In Foundation Service Collection)
Author-Email: Carsten Igel <cig@bite-that-bit.de>
License: MIT
Project-URL: homepage, https://github.com/carstencodes/pdm-pfsc
Requires-Python: >=3.9
Requires-Dist: pyproject-metadata>=0.9.1
Requires-Dist: pdm>=2.24.2
